{
  "data": {
    "article": {},
    "attachments": {},
    "author_id": "1452123941686976519",
    "conversation_id": "1863258269030154426",
    "created_at": "2024-12-01T16:44:04.000Z",
    "edit_controls": {
      "editable_until": "2024-12-01T17:44:04.000Z",
      "edits_remaining": 5,
      "is_edit_eligible": false
    },
    "edit_history_tweet_ids": [
      "1863262802888228969"
    ],
    "entities": {
      "annotations": [
        {
          "end": 17,
          "normalized_text": "朋朋",
          "probability": 0.9254,
          "start": 16,
          "type": "Person"
        }
      ],
      "mentions": [
        {
          "end": 12,
          "id": "1244249898288992257",
          "start": 0,
          "username": "Sneaky_2006"
        }
      ]
    },
    "geo": {},
    "id": "1863262802888228969",
    "in_reply_to_user_id": "1244249898288992257",
    "lang": "ja",
    "note_tweet": {
      "entities": {}
    },
    "possibly_sensitive": false,
    "public_metrics": {
      "bookmark_count": 0,
      "impression_count": 0,
      "like_count": 0,
      "quote_count": 0,
      "reply_count": 0,
      "retweet_count": 0
    },
    "referenced_tweets": [
      {
        "id": "1863258269030154426",
        "type": "replied_to"
      }
    ],
    "reply_settings": "everyone",
    "text": "@Sneaky_2006 没事的朋朋！总有一天会遇到自己的好桃花(｡･ω･｡)ﾉ(*≧ω≦)"
  },
  "includes": {
    "tweets": [
      {
        "article": {},
        "attachments": {},
        "author_id": "1452123941686976519",
        "conversation_id": "1863258269030154426",
        "created_at": "2024-12-01T16:44:04.000Z",
        "edit_controls": {
          "editable_until": "2024-12-01T17:44:04.000Z",
          "edits_remaining": 5,
          "is_edit_eligible": false
        },
        "edit_history_tweet_ids": [
          "1863262802888228969"
        ],
        "entities": {
          "annotations": [
            {
              "end": 17,
              "normalized_text": "朋朋",
              "probability": 0.9254,
              "start": 16,
              "type": "Person"
            }
          ],
          "mentions": [
            {
              "end": 12,
              "id": "1244249898288992257",
              "start": 0,
              "username": "Sneaky_2006"
            }
          ]
        },
        "geo": {},
        "id": "1863262802888228969",
        "in_reply_to_user_id": "1244249898288992257",
        "lang": "ja",
        "note_tweet": {
          "entities": {}
        },
        "possibly_sensitive": false,
        "public_metrics": {
          "bookmark_count": 0,
          "impression_count": 0,
          "like_count": 0,
          "quote_count": 0,
          "reply_count": 0,
          "retweet_count": 0
        },
        "referenced_tweets": [
          {
            "id": "1863258269030154426",
            "type": "replied_to"
          }
        ],
        "reply_settings": "everyone",
        "text": "@Sneaky_2006 没事的朋朋！总有一天会遇到自己的好桃花(｡･ω･｡)ﾉ(*≧ω≦)"
      },
      {
        "article": {},
        "attachments": {},
        "author_id": "1244249898288992257",
        "conversation_id": "1863258269030154426",
        "created_at": "2024-12-01T16:26:03.000Z",
        "edit_controls": {
          "editable_until": "2024-12-01T17:26:03.000Z",
          "edits_remaining": 5,
          "is_edit_eligible": false
        },
        "edit_history_tweet_ids": [
          "1863258269030154426"
        ],
        "entities": {},
        "geo": {},
        "id": "1863258269030154426",
        "lang": "zh",
        "note_tweet": {
          "entities": {}
        },
        "possibly_sensitive": false,
        "public_metrics": {
          "bookmark_count": 0,
          "impression_count": 8,
          "like_count": 1,
          "quote_count": 0,
          "reply_count": 2,
          "retweet_count": 0
        },
        "reply_settings": "everyone",
        "text": "現在算午夜時間，來靠北自己沒桃花怎麼樣？"
      }
    ],
    "users": [
      {
        "created_at": "2021-10-24T04:05:30.000Z",
        "description": "自我生存娱乐空间 内可能含有NSFW shtwt🚫bi🏳️‍🌈/ they最近捣鼓：DOL/BG3/oc世界观/TMNT/COT/恐影 大概淡坑：COD/MK 不善表达 但是还算可以 懒惰的同人女 会突然产出想法 GB GL大于BL BG  是成年账户",
        "id": "1452123941686976519",
        "name": "鸦鸦臀肉",
        "pinned_tweet_id": "1852942963988631891",
        "profile_image_url": "https://pbs.twimg.com/profile_images/1853390447168921600/rc6MWWGZ_normal.jpg",
        "protected": false,
        "public_metrics": {
          "followers_count": 773,
          "following_count": 2920,
          "like_count": 20862,
          "listed_count": 2,
          "media_count": 1107,
          "tweet_count": 18317
        },
        "username": "C21Koy_7c",
        "verified": false
      },
      {
        "created_at": "2020-03-29T13:09:19.000Z",
        "description": "嘿對，我知道很突然，\n但我十八了呦。\n這裡偶爾會出現奇怪的口嗨，\n還會用恐怖的發言創死你家的留言區。\n無情轉推機，會推給你一些亂七八糟但我很愛的玩意兒。\n還有，這裡是本人心理年齡三歲，黃推見一個ban一個",
        "id": "1244249898288992257",
        "location": "墓阿埔",
        "name": "偷偷摸摸/星希",
        "pinned_tweet_id": "1847163820034478345",
        "profile_image_url": "https://pbs.twimg.com/profile_images/1852060380539023360/_HZo90km_normal.jpg",
        "protected": false,
        "public_metrics": {
          "followers_count": 137,
          "following_count": 2712,
          "like_count": 85651,
          "listed_count": 0,
          "media_count": 99,
          "tweet_count": 4651
        },
        "username": "Sneaky_2006",
        "verified": false
      }
    ]
  }
}