{
  "data": {
    "article": {},
    "attachments": {
      "media_keys": [
        "3_1993590863650488320"
      ],
      "media_source_tweet_id": [
        "1993591023596081295"
      ]
    },
    "author_id": "1452123941686976519",
    "conversation_id": "1993637267269661145",
    "created_at": "2025-11-26T11:05:39.000Z",
    "edit_controls": {
      "editable_until": "2025-11-26T12:05:39.000Z",
      "edits_remaining": 5,
      "is_edit_eligible": false
    },
    "edit_history_tweet_ids": [
      "1993637267269661145"
    ],
    "entities": {
      "mentions": [
        {
          "end": 13,
          "id": "781794508602126336",
          "start": 3,
          "username": "ironyyof_"
        }
      ],
      "urls": [
        {
          "display_url": "pic.x.com/8ZRLYafIcU",
          "end": 48,
          "expanded_url": "https://x.com/ironyyof_/status/1993591023596081295/photo/1",
          "media_key": "3_1993590863650488320",
          "start": 25,
          "url": "https://t.co/8ZRLYafIcU"
        }
      ]
    },
    "geo": {},
    "id": "1993637267269661145",
    "lang": "ko",
    "note_tweet": {
      "entities": {}
    },
    "possibly_sensitive": false,
    "public_metrics": {
      "bookmark_count": 0,
      "impression_count": 0,
      "like_count": 0,
      "quote_count": 0,
      "reply_count": 0,
      "retweet_count": 121
    },
    "referenced_tweets": [
      {
        "id": "1993591023596081295",
        "type": "retweeted"
      }
    ],
    "reply_settings": "everyone",
    "text": "RT @ironyyof_: 힐밴이야 겐지오빠 https://t.co/8ZRLYafIcU"
  },
  "includes": {
    "media": [
      {
        "height": 1300,
        "media_key": "3_1993590863650488320",
        "public_metrics": {},
        "type": "photo",
        "url": "https://pbs.twimg.com/media/G6qoU_daAAAgLoh.jpg",
        "width": 1700
      }
    ],
    "tweets": [
      {
        "article": {},
        "attachments": {
          "media_keys": [
            "3_1993590863650488320"
          ],
          "media_source_tweet_id": [
            "1993591023596081295"
          ]
        },
        "author_id": "1452123941686976519",
        "conversation_id": "1993637267269661145",
        "created_at": "2025-11-26T11:05:39.000Z",
        "edit_controls": {
          "editable_until": "2025-11-26T12:05:39.000Z",
          "edits_remaining": 5,
          "is_edit_eligible": false
        },
        "edit_history_tweet_ids": [
          "1993637267269661145"
        ],
        "entities": {
          "mentions": [
            {
              "end": 13,
              "id": "781794508602126336",
              "start": 3,
              "username": "ironyyof_"
            }
          ],
          "urls": [
            {
              "display_url": "pic.x.com/8ZRLYafIcU",
              "end": 48,
              "expanded_url": "https://x.com/ironyyof_/status/1993591023596081295/photo/1",
              "media_key": "3_1993590863650488320",
              "start": 25,
              "url": "https://t.co/8ZRLYafIcU"
            }
          ]
        },
        "geo": {},
        "id": "1993637267269661145",
        "lang": "ko",
        "note_tweet": {
          "entities": {}
        },
        "possibly_sensitive": false,
        "public_metrics": {
          "bookmark_count": 0,
          "impression_count": 0,
          "like_count": 0,
          "quote_count": 0,
          "reply_count": 0,
          "retweet_count": 121
        },
        "referenced_tweets": [
          {
            "id": "1993591023596081295",
            "type": "retweeted"
          }
        ],
        "reply_settings": "everyone",
        "text": "RT @ironyyof_: 힐밴이야 겐지오빠 https://t.co/8ZRLYafIcU"
      },
      {
        "article": {},
        "attachments": {
          "media_keys": [
            "3_1993590863650488320"
          ]
        },
        "author_id": "781794508602126336",
        "conversation_id": "1993591023596081295",
        "created_at": "2025-11-26T08:01:53.000Z",
        "edit_controls": {
          "editable_until": "2025-11-26T09:01:53.000Z",
          "edits_remaining": 5,
          "is_edit_eligible": true
        },
        "edit_history_tweet_ids": [
          "1993591023596081295"
        ],
        "entities": {
          "urls": [
            {
              "display_url": "pic.x.com/8ZRLYafIcU",
              "end": 33,
              "expanded_url": "https://x.com/ironyyof_/status/1993591023596081295/photo/1",
              "media_key": "3_1993590863650488320",
              "start": 10,
              "url": "https://t.co/8ZRLYafIcU"
            }
          ]
        },
        "geo": {},
        "id": "1993591023596081295",
        "lang": "ko",
        "note_tweet": {
          "entities": {}
        },
        "possibly_sensitive": false,
        "public_metrics": {
          "bookmark_count": 49,
          "impression_count": 7269,
          "like_count": 268,
          "quote_count": 71,
          "reply_count": 0,
          "retweet_count": 121
        },
        "reply_settings": "everyone",
        "text": "힐밴이야 겐지오빠 https://t.co/8ZRLYafIcU"
      }
    ],
    "users": [
      {
        "created_at": "2021-10-24T04:05:30.000Z",
        "description": "自我生存娱乐空间 内可能含有NSFW 有SH｜pills💊 ｜20+警告⚠️ ｜they｜不善表达 我想复健产粮…懒惰的同人爱好者 是成年账户 全是翻译器 是精神病 温和 随时锁推 业余的 很笨 有不对的请不要说我 对异形勃起 欢迎讨论 不会讨厌谁 叫我什么都可以 不会外语 一切用翻译器翻的",
        "id": "1452123941686976519",
        "name": "盐制肉鸦",
        "pinned_tweet_id": "1971924675585568891",
        "profile_image_url": "https://pbs.twimg.com/profile_images/1987482127756410880/kunx4knz_normal.jpg",
        "protected": false,
        "public_metrics": {
          "followers_count": 895,
          "following_count": 3165,
          "like_count": 26254,
          "listed_count": 5,
          "media_count": 1773,
          "tweet_count": 24968
        },
        "username": "C21Koy_7c",
        "verified": false
      },
      {
        "created_at": "2016-09-30T09:55:10.000Z",
        "description": "여우 신령님은 혈당도 조절해줘요",
        "id": "781794508602126336",
        "location": "좋아하는 거 그려요 | 장르팔비추‼️",
        "name": "irony",
        "pinned_tweet_id": "1993591023596081295",
        "profile_image_url": "https://pbs.twimg.com/profile_images/1987550901469581312/q8RAS0ie_normal.jpg",
        "protected": false,
        "public_metrics": {
          "followers_count": 524,
          "following_count": 57,
          "like_count": 580,
          "listed_count": 3,
          "media_count": 13,
          "tweet_count": 57
        },
        "username": "ironyyof_",
        "verified": false
      }
    ]
  }
}