{
  "data": {
    "article": {},
    "attachments": {
      "media_keys": [
        "3_1979144018131927041",
        "3_1979144044082016256"
      ],
      "media_source_tweet_id": [
        "1979144057470304533",
        "1979144057470304533"
      ]
    },
    "author_id": "1452123941686976519",
    "conversation_id": "1979253536799306049",
    "created_at": "2025-10-17T18:29:50.000Z",
    "edit_controls": {
      "editable_until": "2025-10-17T19:29:50.000Z",
      "edits_remaining": 5,
      "is_edit_eligible": false
    },
    "edit_history_tweet_ids": [
      "1979253536799306049"
    ],
    "entities": {
      "mentions": [
        {
          "end": 13,
          "id": "1858148276463345664",
          "start": 3,
          "username": "Ra1noppa1"
        }
      ],
      "urls": [
        {
          "display_url": "pic.x.com/rhNXPQpWMg",
          "end": 38,
          "expanded_url": "https://x.com/Ra1noppa1/status/1979144057470304533/photo/1",
          "media_key": "3_1979144018131927041",
          "start": 15,
          "url": "https://t.co/rhNXPQpWMg"
        },
        {
          "display_url": "pic.x.com/rhNXPQpWMg",
          "end": 38,
          "expanded_url": "https://x.com/Ra1noppa1/status/1979144057470304533/photo/1",
          "media_key": "3_1979144044082016256",
          "start": 15,
          "url": "https://t.co/rhNXPQpWMg"
        }
      ]
    },
    "geo": {},
    "id": "1979253536799306049",
    "lang": "zxx",
    "note_tweet": {
      "entities": {}
    },
    "possibly_sensitive": false,
    "public_metrics": {
      "bookmark_count": 0,
      "impression_count": 0,
      "like_count": 0,
      "quote_count": 0,
      "reply_count": 0,
      "retweet_count": 107
    },
    "referenced_tweets": [
      {
        "id": "1979144057470304533",
        "type": "retweeted"
      }
    ],
    "reply_settings": "everyone",
    "text": "RT @Ra1noppa1: https://t.co/rhNXPQpWMg"
  },
  "includes": {
    "media": [
      {
        "height": 1254,
        "media_key": "3_1979144018131927041",
        "public_metrics": {},
        "type": "photo",
        "url": "https://pbs.twimg.com/media/G3dU_6AXwAEuM1a.jpg",
        "width": 2500
      },
      {
        "height": 1254,
        "media_key": "3_1979144044082016256",
        "public_metrics": {},
        "type": "photo",
        "url": "https://pbs.twimg.com/media/G3dVBarWsAA166F.jpg",
        "width": 2500
      }
    ],
    "tweets": [
      {
        "article": {},
        "attachments": {
          "media_keys": [
            "3_1979144018131927041",
            "3_1979144044082016256"
          ],
          "media_source_tweet_id": [
            "1979144057470304533",
            "1979144057470304533"
          ]
        },
        "author_id": "1452123941686976519",
        "conversation_id": "1979253536799306049",
        "created_at": "2025-10-17T18:29:50.000Z",
        "edit_controls": {
          "editable_until": "2025-10-17T19:29:50.000Z",
          "edits_remaining": 5,
          "is_edit_eligible": false
        },
        "edit_history_tweet_ids": [
          "1979253536799306049"
        ],
        "entities": {
          "mentions": [
            {
              "end": 13,
              "id": "1858148276463345664",
              "start": 3,
              "username": "Ra1noppa1"
            }
          ],
          "urls": [
            {
              "display_url": "pic.x.com/rhNXPQpWMg",
              "end": 38,
              "expanded_url": "https://x.com/Ra1noppa1/status/1979144057470304533/photo/1",
              "media_key": "3_1979144018131927041",
              "start": 15,
              "url": "https://t.co/rhNXPQpWMg"
            },
            {
              "display_url": "pic.x.com/rhNXPQpWMg",
              "end": 38,
              "expanded_url": "https://x.com/Ra1noppa1/status/1979144057470304533/photo/1",
              "media_key": "3_1979144044082016256",
              "start": 15,
              "url": "https://t.co/rhNXPQpWMg"
            }
          ]
        },
        "geo": {},
        "id": "1979253536799306049",
        "lang": "zxx",
        "note_tweet": {
          "entities": {}
        },
        "possibly_sensitive": false,
        "public_metrics": {
          "bookmark_count": 0,
          "impression_count": 0,
          "like_count": 0,
          "quote_count": 0,
          "reply_count": 0,
          "retweet_count": 107
        },
        "referenced_tweets": [
          {
            "id": "1979144057470304533",
            "type": "retweeted"
          }
        ],
        "reply_settings": "everyone",
        "text": "RT @Ra1noppa1: https://t.co/rhNXPQpWMg"
      },
      {
        "article": {},
        "attachments": {
          "media_keys": [
            "3_1979144018131927041",
            "3_1979144044082016256"
          ]
        },
        "author_id": "1858148276463345664",
        "conversation_id": "1979144057470304533",
        "created_at": "2025-10-17T11:14:48.000Z",
        "edit_controls": {
          "editable_until": "2025-10-17T12:14:48.000Z",
          "edits_remaining": 5,
          "is_edit_eligible": true
        },
        "edit_history_tweet_ids": [
          "1979144057470304533"
        ],
        "entities": {
          "urls": [
            {
              "display_url": "pic.x.com/rhNXPQpWMg",
              "end": 23,
              "expanded_url": "https://x.com/Ra1noppa1/status/1979144057470304533/photo/1",
              "media_key": "3_1979144018131927041",
              "start": 0,
              "url": "https://t.co/rhNXPQpWMg"
            },
            {
              "display_url": "pic.x.com/rhNXPQpWMg",
              "end": 23,
              "expanded_url": "https://x.com/Ra1noppa1/status/1979144057470304533/photo/1",
              "media_key": "3_1979144044082016256",
              "start": 0,
              "url": "https://t.co/rhNXPQpWMg"
            },
            {
              "display_url": "x.com/Ra1noppa1/stat…",
              "end": 47,
              "expanded_url": "https://twitter.com/Ra1noppa1/status/1962249778697507151",
              "start": 24,
              "url": "https://t.co/Z5LeVKWjlr"
            }
          ]
        },
        "geo": {},
        "id": "1979144057470304533",
        "lang": "zxx",
        "note_tweet": {
          "entities": {}
        },
        "possibly_sensitive": false,
        "public_metrics": {
          "bookmark_count": 5,
          "impression_count": 7855,
          "like_count": 120,
          "quote_count": 9,
          "reply_count": 0,
          "retweet_count": 107
        },
        "referenced_tweets": [
          {
            "id": "1962249778697507151",
            "type": "quoted"
          }
        ],
        "reply_settings": "everyone",
        "text": "https://t.co/rhNXPQpWMg https://t.co/Z5LeVKWjlr"
      }
    ],
    "users": [
      {
        "created_at": "2021-10-24T04:05:30.000Z",
        "description": "自我生存娱乐空间 内可能含有NSFW 有SH｜pills💊 ｜20+警告⚠️ ｜they｜不善表达 我想复健产粮…懒惰的同人爱好者 是成年账户 全是翻译器 是精神病 温和 随时锁推 业余的 很笨 有不对的请不要说我 对异形勃起 欢迎讨论 不会讨厌谁 叫我什么都可以 不会外语 一切用翻译器翻的",
        "id": "1452123941686976519",
        "name": "盐制肉鸦",
        "pinned_tweet_id": "1971924675585568891",
        "profile_image_url": "https://pbs.twimg.com/profile_images/1964100290095042560/8WRhPH87_normal.jpg",
        "protected": false,
        "public_metrics": {
          "followers_count": 847,
          "following_count": 3112,
          "like_count": 24863,
          "listed_count": 5,
          "media_count": 1630,
          "tweet_count": 23847
        },
        "username": "C21Koy_7c",
        "verified": false
      },
      {
        "created_at": "2024-11-17T14:00:53.000Z",
        "description": "",
        "id": "1858148276463345664",
        "name": "정지훈",
        "pinned_tweet_id": "1960804938390626549",
        "profile_image_url": "https://pbs.twimg.com/profile_images/1978583015032012800/Ukj0uRS0_normal.jpg",
        "protected": false,
        "public_metrics": {
          "followers_count": 709,
          "following_count": 45,
          "like_count": 3875,
          "listed_count": 0,
          "media_count": 233,
          "tweet_count": 2982
        },
        "username": "Ra1noppa1",
        "verified": false
      }
    ]
  }
}