{
  "data": {
    "article": {},
    "attachments": {
      "media_keys": [
        "3_1945200373519589376"
      ],
      "media_source_tweet_id": [
        "1945200387994100223"
      ]
    },
    "author_id": "1452123941686976519",
    "context_annotations": [
      {
        "domain": {
          "description": "Categories within Brand Verticals that narrow down the scope of Brands",
          "id": "46",
          "name": "Business Taxonomy"
        },
        "entity": {
          "description": "Brands, companies, advertisers and every non-person handle with the profit intent related to softwares, apps, communication equipments, hardwares",
          "id": "1557697333571112960",
          "name": "Technology Business"
        }
      },
      {
        "domain": {
          "description": "Brands and Companies",
          "id": "47",
          "name": "Brand"
        },
        "entity": {
          "id": "1721576765879980032",
          "name": "Grok Ai"
        }
      },
      {
        "domain": {
          "description": "Products created by Brands.  Examples: Ford Explorer, Apple iPhone.",
          "id": "48",
          "name": "Product"
        },
        "entity": {
          "id": "1721576765879980032",
          "name": "Grok Ai"
        }
      },
      {
        "domain": {
          "description": "A taxonomy of user interests. ",
          "id": "131",
          "name": "Unified Twitter Taxonomy"
        },
        "entity": {
          "description": "Technology and computing",
          "id": "848920371311001600",
          "name": "Technology"
        }
      }
    ],
    "conversation_id": "1945618584811835490",
    "created_at": "2025-07-16T22:56:33.000Z",
    "edit_controls": {
      "editable_until": "2025-07-16T23:56:33.000Z",
      "edits_remaining": 5,
      "is_edit_eligible": false
    },
    "edit_history_tweet_ids": [
      "1945618584811835490"
    ],
    "entities": {
      "hashtags": [
        {
          "end": 21,
          "start": 17,
          "tag": "Ani"
        },
        {
          "end": 29,
          "start": 22,
          "tag": "GrokAI"
        }
      ],
      "mentions": [
        {
          "end": 15,
          "id": "1403560446943121411",
          "start": 3,
          "username": "harucyannnn"
        }
      ],
      "urls": [
        {
          "display_url": "pic.x.com/8OMtWh69HE",
          "end": 53,
          "expanded_url": "https://x.com/harucyannnn/status/1945200387994100223/photo/1",
          "media_key": "3_1945200373519589376",
          "start": 30,
          "url": "https://t.co/8OMtWh69HE"
        }
      ]
    },
    "geo": {},
    "id": "1945618584811835490",
    "lang": "qme",
    "note_tweet": {
      "entities": {}
    },
    "possibly_sensitive": false,
    "public_metrics": {
      "bookmark_count": 0,
      "impression_count": 0,
      "like_count": 0,
      "quote_count": 0,
      "reply_count": 0,
      "retweet_count": 2134
    },
    "referenced_tweets": [
      {
        "id": "1945200387994100223",
        "type": "retweeted"
      }
    ],
    "reply_settings": "everyone",
    "text": "RT @harucyannnn: #Ani #GrokAI https://t.co/8OMtWh69HE"
  },
  "includes": {
    "media": [
      {
        "height": 2048,
        "media_key": "3_1945200373519589376",
        "public_metrics": {},
        "type": "photo",
        "url": "https://pbs.twimg.com/media/Gv69bwCXoAAwsv_.jpg",
        "width": 1448
      }
    ],
    "tweets": [
      {
        "article": {},
        "attachments": {
          "media_keys": [
            "3_1945200373519589376"
          ],
          "media_source_tweet_id": [
            "1945200387994100223"
          ]
        },
        "author_id": "1452123941686976519",
        "context_annotations": [
          {
            "domain": {
              "description": "Categories within Brand Verticals that narrow down the scope of Brands",
              "id": "46",
              "name": "Business Taxonomy"
            },
            "entity": {
              "description": "Brands, companies, advertisers and every non-person handle with the profit intent related to softwares, apps, communication equipments, hardwares",
              "id": "1557697333571112960",
              "name": "Technology Business"
            }
          },
          {
            "domain": {
              "description": "Brands and Companies",
              "id": "47",
              "name": "Brand"
            },
            "entity": {
              "id": "1721576765879980032",
              "name": "Grok Ai"
            }
          },
          {
            "domain": {
              "description": "Products created by Brands.  Examples: Ford Explorer, Apple iPhone.",
              "id": "48",
              "name": "Product"
            },
            "entity": {
              "id": "1721576765879980032",
              "name": "Grok Ai"
            }
          },
          {
            "domain": {
              "description": "A taxonomy of user interests. ",
              "id": "131",
              "name": "Unified Twitter Taxonomy"
            },
            "entity": {
              "description": "Technology and computing",
              "id": "848920371311001600",
              "name": "Technology"
            }
          }
        ],
        "conversation_id": "1945618584811835490",
        "created_at": "2025-07-16T22:56:33.000Z",
        "edit_controls": {
          "editable_until": "2025-07-16T23:56:33.000Z",
          "edits_remaining": 5,
          "is_edit_eligible": false
        },
        "edit_history_tweet_ids": [
          "1945618584811835490"
        ],
        "entities": {
          "hashtags": [
            {
              "end": 21,
              "start": 17,
              "tag": "Ani"
            },
            {
              "end": 29,
              "start": 22,
              "tag": "GrokAI"
            }
          ],
          "mentions": [
            {
              "end": 15,
              "id": "1403560446943121411",
              "start": 3,
              "username": "harucyannnn"
            }
          ],
          "urls": [
            {
              "display_url": "pic.x.com/8OMtWh69HE",
              "end": 53,
              "expanded_url": "https://x.com/harucyannnn/status/1945200387994100223/photo/1",
              "media_key": "3_1945200373519589376",
              "start": 30,
              "url": "https://t.co/8OMtWh69HE"
            }
          ]
        },
        "geo": {},
        "id": "1945618584811835490",
        "lang": "qme",
        "note_tweet": {
          "entities": {}
        },
        "possibly_sensitive": false,
        "public_metrics": {
          "bookmark_count": 0,
          "impression_count": 0,
          "like_count": 0,
          "quote_count": 0,
          "reply_count": 0,
          "retweet_count": 2134
        },
        "referenced_tweets": [
          {
            "id": "1945200387994100223",
            "type": "retweeted"
          }
        ],
        "reply_settings": "everyone",
        "text": "RT @harucyannnn: #Ani #GrokAI https://t.co/8OMtWh69HE"
      },
      {
        "article": {},
        "attachments": {
          "media_keys": [
            "3_1945200373519589376"
          ]
        },
        "author_id": "1403560446943121411",
        "context_annotations": [
          {
            "domain": {
              "description": "Categories within Brand Verticals that narrow down the scope of Brands",
              "id": "46",
              "name": "Business Taxonomy"
            },
            "entity": {
              "description": "Brands, companies, advertisers and every non-person handle with the profit intent related to softwares, apps, communication equipments, hardwares",
              "id": "1557697333571112960",
              "name": "Technology Business"
            }
          },
          {
            "domain": {
              "description": "Brands and Companies",
              "id": "47",
              "name": "Brand"
            },
            "entity": {
              "id": "1721576765879980032",
              "name": "Grok Ai"
            }
          },
          {
            "domain": {
              "description": "Products created by Brands.  Examples: Ford Explorer, Apple iPhone.",
              "id": "48",
              "name": "Product"
            },
            "entity": {
              "id": "1721576765879980032",
              "name": "Grok Ai"
            }
          },
          {
            "domain": {
              "description": "A taxonomy of user interests. ",
              "id": "131",
              "name": "Unified Twitter Taxonomy"
            },
            "entity": {
              "description": "Technology and computing",
              "id": "848920371311001600",
              "name": "Technology"
            }
          }
        ],
        "conversation_id": "1945200387994100223",
        "created_at": "2025-07-15T19:14:47.000Z",
        "edit_controls": {
          "editable_until": "2025-07-15T20:14:47.000Z",
          "edits_remaining": 5,
          "is_edit_eligible": true
        },
        "edit_history_tweet_ids": [
          "1945200387994100223"
        ],
        "entities": {
          "hashtags": [
            {
              "end": 4,
              "start": 0,
              "tag": "Ani"
            },
            {
              "end": 12,
              "start": 5,
              "tag": "GrokAI"
            }
          ],
          "urls": [
            {
              "display_url": "pic.x.com/8OMtWh69HE",
              "end": 36,
              "expanded_url": "https://x.com/harucyannnn/status/1945200387994100223/photo/1",
              "media_key": "3_1945200373519589376",
              "start": 13,
              "url": "https://t.co/8OMtWh69HE"
            }
          ]
        },
        "geo": {},
        "id": "1945200387994100223",
        "lang": "qme",
        "note_tweet": {
          "entities": {}
        },
        "possibly_sensitive": false,
        "public_metrics": {
          "bookmark_count": 4820,
          "impression_count": 373565,
          "like_count": 27710,
          "quote_count": 16,
          "reply_count": 32,
          "retweet_count": 2134
        },
        "reply_settings": "everyone",
        "text": "#Ani #GrokAI https://t.co/8OMtWh69HE"
      }
    ],
    "users": [
      {
        "created_at": "2021-10-24T04:05:30.000Z",
        "description": "自我生存娱乐空间 内可能含有NSFW 有SH｜pills💊 ｜20+警告⚠️ ｜they｜不善表达 我想复健产粮…懒惰的同人爱好者 是成年账户 全是翻译器 是精神病 温和 随时锁推 业余的 很笨 有不对的请不要说我 对异形勃起 欢迎讨论 不会讨厌谁 叫我什么都可以 不会外语 一切用翻译器翻的",
        "id": "1452123941686976519",
        "name": "盐制肉鸦",
        "pinned_tweet_id": "1929299764497019155",
        "profile_image_url": "https://pbs.twimg.com/profile_images/1918279695461933056/VhXhwxKB_normal.jpg",
        "protected": false,
        "public_metrics": {
          "followers_count": 782,
          "following_count": 3024,
          "like_count": 23576,
          "listed_count": 3,
          "media_count": 1476,
          "tweet_count": 22705
        },
        "username": "C21Koy_7c",
        "verified": false
      },
      {
        "created_at": "2021-06-12T03:51:11.000Z",
        "description": "Follow for more art I made!",
        "id": "1403560446943121411",
        "name": "HaruChan",
        "profile_image_url": "https://pbs.twimg.com/profile_images/1881923363821756416/0SM9LfD2_normal.jpg",
        "protected": false,
        "public_metrics": {
          "followers_count": 1597,
          "following_count": 140,
          "like_count": 91,
          "listed_count": 8,
          "media_count": 21,
          "tweet_count": 67
        },
        "username": "harucyannnn",
        "verified": false
      }
    ]
  }
}